sqlite_utils_sqlite_jiff/__init__.py
sqlite_utils_sqlite_jiff-0.0.1a2.dist-info/METADATA
sqlite_utils_sqlite_jiff-0.0.1a2.dist-info/WHEEL
sqlite_utils_sqlite_jiff-0.0.1a2.dist-info/entry_points.txt
sqlite_utils_sqlite_jiff-0.0.1a2.dist-info/top_level.txt
sqlite_utils_sqlite_jiff-0.0.1a2.dist-info/RECORD
