Metadata-Version: 2.1
Name: sqlite-utils-sqlite-jiff
Version: 0.0.1a2
Home-page: https://TODO.com
Author: TODO
License: MIT License, Apache License, Version 2.0
Requires-Dist: sqlite-utils
Requires-Dist: sqlite-jiff (==0.0.1-alpha.2)
